{
    "routes": [
        [
            {
                "node_id": 0,
                "arrival_time_det": 480
            },
            {
                "node_id": 1,
                "arrival_time_det": 592
            },
            {
                "node_id": 17,
                "arrival_time_det": 749
            },
            {
                "node_id": 5,
                "arrival_time_det": 784
            },
            {
                "node_id": 0,
                "arrival_time_det": 831
            }
        ],
        [
            {
                "node_id": 0,
                "arrival_time_det": 0
            },
            {
                "node_id": 8,
                "arrival_time_det": 566
            },
            {
                "node_id": 14,
                "arrival_time_det": 640
            },
            {
                "node_id": 9,
                "arrival_time_det": 690
            },
            {
                "node_id": 20,
                "arrival_time_det": 720
            },
            {
                "node_id": 2,
                "arrival_time_det": 760
            },
            {
                "node_id": 0,
                "arrival_time_det": 821
            }
        ],
        [
            {
                "node_id": 0,
                "arrival_time_det": 0
            },
            {
                "node_id": 4,
                "arrival_time_det": 651
            },
            {
                "node_id": 11,
                "arrival_time_det": 697
            },
            {
                "node_id": 18,
                "arrival_time_det": 719
            },
            {
                "node_id": 19,
                "arrival_time_det": 803
            },
            {
                "node_id": 0,
                "arrival_time_det": 861
            }
        ],
        [
            {
                "node_id": 0,
                "arrival_time_det": 0
            },
            {
                "node_id": 15,
                "arrival_time_det": 671
            },
            {
                "node_id": 16,
                "arrival_time_det": 700
            },
            {
                "node_id": 6,
                "arrival_time_det": 728
            },
            {
                "node_id": 10,
                "arrival_time_det": 749
            },
            {
                "node_id": 0,
                "arrival_time_det": 816
            }
        ],
        [
            {
                "node_id": 0,
                "arrival_time_det": 0
            },
            {
                "node_id": 13,
                "arrival_time_det": 603
            },
            {
                "node_id": 7,
                "arrival_time_det": 669
            },
            {
                "node_id": 3,
                "arrival_time_det": 688
            },
            {
                "node_id": 12,
                "arrival_time_det": 713
            },
            {
                "node_id": 0,
                "arrival_time_det": 761
            }
        ],
        [
            {
                "node_id": 0,
                "arrival_time_det": 0
            },
            {
                "node_id": 0,
                "arrival_time_det": 0
            }
        ]
    ],
    "total_distance": 459,
    "total_cost": 277.8333333333333,
    "status": "Optimal/Feasible",
    "instance_file": "N020_V006_I081.json",
    "N": 20,
    "V": 6,
    "Q": 79,
    "solve_time_seconds": 30.002679347991943,
    "policy_type": "Deterministic_ORTools_Strategy"
}