{
    "num_customers": 20,
    "num_vehicles": 10,
    "vehicle_capacity": 47,
    "depot": {
        "id": 0,
        "x": 50,
        "y": 50,
        "E": 480,
        "L": 960
    },
    "customers": [
        {
            "id": 1,
            "x": 58.516386012367306,
            "y": 49.57676769075171,
            "demand": 21,
            "E": 682.5314063421614,
            "L": 858.5333416332018,
            "mean_service_time": 10.0
        },
        {
            "id": 2,
            "x": 42.706572094603025,
            "y": 42.69350581214124,
            "demand": 21,
            "E": 508.6327696191101,
            "L": 672.8442168363823,
            "mean_service_time": 10.0
        },
        {
            "id": 3,
            "x": 85.41775086451729,
            "y": 41.8250310014564,
            "demand": 23,
            "E": 561.5895888913174,
            "L": 626.9969449680599,
            "mean_service_time": 10.0
        },
        {
            "id": 4,
            "x": 75.6817428001289,
            "y": 96.98965470440082,
            "demand": 21,
            "E": 762.8778773427707,
            "L": 873.4240349490116,
            "mean_service_time": 10.0
        },
        {
            "id": 5,
            "x": 33.51125259784591,
            "y": 16.04092716440071,
            "demand": 11,
            "E": 716.9085623200174,
            "L": 882.7701932752221,
            "mean_service_time": 10.0
        },
        {
            "id": 6,
            "x": 21.881238295406146,
            "y": 33.45667434842484,
            "demand": 24,
            "E": 546.7135683120545,
            "L": 706.4428255844679,
            "mean_service_time": 10.0
        },
        {
            "id": 7,
            "x": 35.46945017514243,
            "y": 82.89606360513993,
            "demand": 24,
            "E": 508.6986274301435,
            "L": 627.6019307628565,
            "mean_service_time": 10.0
        },
        {
            "id": 8,
            "x": 90.18507716706603,
            "y": 82.45495873712068,
            "demand": 17,
            "E": 783.2171073606648,
            "L": 875.6667387373453,
            "mean_service_time": 10.0
        },
        {
            "id": 9,
            "x": 42.6985542036481,
            "y": 12.362912526353032,
            "demand": 18,
            "E": 481.1737769166733,
            "L": 558.2586854829416,
            "mean_service_time": 10.0
        },
        {
            "id": 10,
            "x": 6.3052588276675925,
            "y": 45.40467423317631,
            "demand": 21,
            "E": 608.5755488974238,
            "L": 788.5563472342185,
            "mean_service_time": 10.0
        },
        {
            "id": 11,
            "x": 90.28696136852257,
            "y": 10.47630563259554,
            "demand": 14,
            "E": 825.1089490169188,
            "L": 947.4353812971812,
            "mean_service_time": 10.0
        },
        {
            "id": 12,
            "x": 38.17609234593764,
            "y": 84.32019501357308,
            "demand": 23,
            "E": 683.5435547031825,
            "L": 768.1428958889976,
            "mean_service_time": 10.0
        },
        {
            "id": 13,
            "x": 58.718231215411244,
            "y": 90.83661104403316,
            "demand": 12,
            "E": 703.8844405366838,
            "L": 790.2031976772649,
            "mean_service_time": 10.0
        },
        {
            "id": 14,
            "x": 15.236837282654081,
            "y": 34.18327506433596,
            "demand": 23,
            "E": 530.6077057172602,
            "L": 703.7801926299484,
            "mean_service_time": 10.0
        },
        {
            "id": 15,
            "x": 21.377595216005663,
            "y": 32.15837519111776,
            "demand": 11,
            "E": 613.3817432271471,
            "L": 728.795189933945,
            "mean_service_time": 10.0
        },
        {
            "id": 16,
            "x": 38.83463346358758,
            "y": 73.16796685291061,
            "demand": 14,
            "E": 705.6605190981824,
            "L": 806.9023685876732,
            "mean_service_time": 10.0
        },
        {
            "id": 17,
            "x": 54.16225471547389,
            "y": 45.66951832518368,
            "demand": 22,
            "E": 745.5209505334535,
            "L": 844.4464991773906,
            "mean_service_time": 10.0
        },
        {
            "id": 18,
            "x": 82.37706571788988,
            "y": 94.57143239764338,
            "demand": 19,
            "E": 545.6263272072819,
            "L": 643.1173722167415,
            "mean_service_time": 10.0
        },
        {
            "id": 19,
            "x": 58.107961392371124,
            "y": 12.747439081379476,
            "demand": 24,
            "E": 862.5446514390853,
            "L": 954.8820317267528,
            "mean_service_time": 10.0
        },
        {
            "id": 20,
            "x": 74.33578953791442,
            "y": 37.25368469807453,
            "demand": 11,
            "E": 607.6525747052679,
            "L": 695.5997015366082,
            "mean_service_time": 10.0
        }
    ]
}