{
    "num_customers": 50,
    "num_vehicles": 25,
    "vehicle_capacity": 42,
    "depot": {
        "id": 0,
        "x": 50,
        "y": 50,
        "E": 480,
        "L": 960
    },
    "customers": [
        {
            "id": 1,
            "x": 70.47185059118956,
            "y": 35.73766922407662,
            "demand": 16,
            "E": 519.6853712024347,
            "L": 584.7731282452544,
            "mean_service_time": 10.0
        },
        {
            "id": 2,
            "x": 25.15433653313557,
            "y": 44.147299125799435,
            "demand": 14,
            "E": 817.3230545944909,
            "L": 882.6210010018538,
            "mean_service_time": 10.0
        },
        {
            "id": 3,
            "x": 38.10762888948123,
            "y": 82.42066822302829,
            "demand": 11,
            "E": 644.2989209722718,
            "L": 709.0962388274764,
            "mean_service_time": 10.0
        },
        {
            "id": 4,
            "x": 0.4879305053829386,
            "y": 3.0414862834035494,
            "demand": 14,
            "E": 786.869341481857,
            "L": 948.0560652539527,
            "mean_service_time": 10.0
        },
        {
            "id": 5,
            "x": 42.988883647891285,
            "y": 84.00526549321764,
            "demand": 22,
            "E": 593.6846194241286,
            "L": 767.4384433106515,
            "mean_service_time": 10.0
        },
        {
            "id": 6,
            "x": 12.495581614233519,
            "y": 79.30828757212969,
            "demand": 19,
            "E": 718.0611177213582,
            "L": 890.9414582406873,
            "mean_service_time": 10.0
        },
        {
            "id": 7,
            "x": 47.660990312238916,
            "y": 92.89677078771443,
            "demand": 12,
            "E": 623.4901980390537,
            "L": 739.6271737485471,
            "mean_service_time": 10.0
        },
        {
            "id": 8,
            "x": 95.40878986494425,
            "y": 65.02701740209082,
            "demand": 20,
            "E": 482.27739905426307,
            "L": 565.4272591386402,
            "mean_service_time": 10.0
        },
        {
            "id": 9,
            "x": 63.29023305881216,
            "y": 20.18746904789337,
            "demand": 11,
            "E": 488.98095906709676,
            "L": 636.0999792791417,
            "mean_service_time": 10.0
        },
        {
            "id": 10,
            "x": 61.36021617209425,
            "y": 77.63481426535911,
            "demand": 22,
            "E": 756.6714702586471,
            "L": 857.79865843094,
            "mean_service_time": 10.0
        },
        {
            "id": 11,
            "x": 39.533304572148666,
            "y": 44.339688618626894,
            "demand": 15,
            "E": 759.7452889841022,
            "L": 824.4535662613004,
            "mean_service_time": 10.0
        },
        {
            "id": 12,
            "x": 61.06298759745673,
            "y": 11.259178048978868,
            "demand": 22,
            "E": 556.7978914371034,
            "L": 674.3068452830981,
            "mean_service_time": 10.0
        },
        {
            "id": 13,
            "x": 6.360949588570652,
            "y": 96.950903096015,
            "demand": 24,
            "E": 540.3182767881365,
            "L": 665.6850285954023,
            "mean_service_time": 10.0
        },
        {
            "id": 14,
            "x": 55.34572472719188,
            "y": 36.27435358335784,
            "demand": 24,
            "E": 558.0059823005569,
            "L": 726.0660559038422,
            "mean_service_time": 10.0
        },
        {
            "id": 15,
            "x": 6.703570545731241,
            "y": 47.31288501651969,
            "demand": 12,
            "E": 496.0487687949951,
            "L": 565.6176942976649,
            "mean_service_time": 10.0
        },
        {
            "id": 16,
            "x": 89.20992302897005,
            "y": 41.65528321979779,
            "demand": 14,
            "E": 589.2126306201956,
            "L": 744.0465438475612,
            "mean_service_time": 10.0
        },
        {
            "id": 17,
            "x": 28.78765392154248,
            "y": 21.65568046154811,
            "demand": 17,
            "E": 595.8954888616987,
            "L": 737.79589309211,
            "mean_service_time": 10.0
        },
        {
            "id": 18,
            "x": 16.279664588774544,
            "y": 65.65040990192117,
            "demand": 21,
            "E": 500.42308477337,
            "L": 624.6846943562882,
            "mean_service_time": 10.0
        },
        {
            "id": 19,
            "x": 58.56357680454707,
            "y": 42.84062029010959,
            "demand": 18,
            "E": 728.1665443028841,
            "L": 802.8787673344646,
            "mean_service_time": 10.0
        },
        {
            "id": 20,
            "x": 15.457080061072737,
            "y": 83.7299318932697,
            "demand": 19,
            "E": 791.4437146006067,
            "L": 893.7545042832368,
            "mean_service_time": 10.0
        },
        {
            "id": 21,
            "x": 84.25323834109733,
            "y": 0.7229715484473376,
            "demand": 11,
            "E": 680.7846204944087,
            "L": 744.5497050341614,
            "mean_service_time": 10.0
        },
        {
            "id": 22,
            "x": 41.31629920157405,
            "y": 27.19539309810546,
            "demand": 12,
            "E": 522.1736953809669,
            "L": 654.9215528740413,
            "mean_service_time": 10.0
        },
        {
            "id": 23,
            "x": 86.1678514119126,
            "y": 79.5589476619456,
            "demand": 23,
            "E": 636.4447238517632,
            "L": 706.2462937241625,
            "mean_service_time": 10.0
        },
        {
            "id": 24,
            "x": 63.34662898968067,
            "y": 79.66090920283865,
            "demand": 17,
            "E": 680.5335353064645,
            "L": 759.6436370601479,
            "mean_service_time": 10.0
        },
        {
            "id": 25,
            "x": 39.25067889591291,
            "y": 23.47713552364864,
            "demand": 15,
            "E": 824.1116871780006,
            "L": 900.2597503664215,
            "mean_service_time": 10.0
        },
        {
            "id": 26,
            "x": 42.77018100844726,
            "y": 72.4384991998116,
            "demand": 22,
            "E": 506.1653016005291,
            "L": 581.1068335090656,
            "mean_service_time": 10.0
        },
        {
            "id": 27,
            "x": 76.07857400457847,
            "y": 52.31868292018582,
            "demand": 11,
            "E": 757.5632089052308,
            "L": 917.13814605026,
            "mean_service_time": 10.0
        },
        {
            "id": 28,
            "x": 99.25718577074619,
            "y": 56.0816523678587,
            "demand": 10,
            "E": 551.9469515386759,
            "L": 638.6685724890422,
            "mean_service_time": 10.0
        },
        {
            "id": 29,
            "x": 15.182663363036164,
            "y": 68.88596871258764,
            "demand": 10,
            "E": 809.8714237761006,
            "L": 908.6313496668381,
            "mean_service_time": 10.0
        },
        {
            "id": 30,
            "x": 93.91401448417935,
            "y": 81.59413232773475,
            "demand": 11,
            "E": 813.5101674193209,
            "L": 936.7163905246857,
            "mean_service_time": 10.0
        },
        {
            "id": 31,
            "x": 46.87090912903006,
            "y": 73.33010474539931,
            "demand": 19,
            "E": 490.31543747585204,
            "L": 647.0333627531544,
            "mean_service_time": 10.0
        },
        {
            "id": 32,
            "x": 53.82176660951414,
            "y": 35.833850239343846,
            "demand": 17,
            "E": 703.3390759292034,
            "L": 868.7676645105842,
            "mean_service_time": 10.0
        },
        {
            "id": 33,
            "x": 28.972350617749743,
            "y": 30.97196956545578,
            "demand": 15,
            "E": 696.6025558984612,
            "L": 809.0466935584715,
            "mean_service_time": 10.0
        },
        {
            "id": 34,
            "x": 17.25445909011123,
            "y": 56.42369009851206,
            "demand": 18,
            "E": 481.0318393501946,
            "L": 599.384045575254,
            "mean_service_time": 10.0
        },
        {
            "id": 35,
            "x": 28.82149045577599,
            "y": 8.494129881658585,
            "demand": 23,
            "E": 697.5888098116639,
            "L": 808.9982797750789,
            "mean_service_time": 10.0
        },
        {
            "id": 36,
            "x": 30.544306767338302,
            "y": 13.22808603863006,
            "demand": 19,
            "E": 794.4945074975005,
            "L": 950.1717284170005,
            "mean_service_time": 10.0
        },
        {
            "id": 37,
            "x": 88.93696629860767,
            "y": 98.36805173210189,
            "demand": 11,
            "E": 740.571009059651,
            "L": 816.6609798204083,
            "mean_service_time": 10.0
        },
        {
            "id": 38,
            "x": 79.9885291616797,
            "y": 69.10649485615006,
            "demand": 18,
            "E": 747.1752015814238,
            "L": 846.4666234324279,
            "mean_service_time": 10.0
        },
        {
            "id": 39,
            "x": 29.25095159731911,
            "y": 80.62643085064506,
            "demand": 17,
            "E": 792.3714750052687,
            "L": 921.5783568362676,
            "mean_service_time": 10.0
        },
        {
            "id": 40,
            "x": 40.47069215260443,
            "y": 66.59345141295657,
            "demand": 13,
            "E": 723.608048945806,
            "L": 809.1095579300321,
            "mean_service_time": 10.0
        },
        {
            "id": 41,
            "x": 89.31264674682036,
            "y": 29.81810645659946,
            "demand": 11,
            "E": 553.0606466341886,
            "L": 719.7543356043923,
            "mean_service_time": 10.0
        },
        {
            "id": 42,
            "x": 82.61500301716686,
            "y": 20.7711618167987,
            "demand": 12,
            "E": 656.2618724031614,
            "L": 796.9604526191139,
            "mean_service_time": 10.0
        },
        {
            "id": 43,
            "x": 77.29303820804361,
            "y": 23.360001960312392,
            "demand": 16,
            "E": 505.3118290123949,
            "L": 580.8214170124486,
            "mean_service_time": 10.0
        },
        {
            "id": 44,
            "x": 93.67445627210047,
            "y": 75.69045724119192,
            "demand": 10,
            "E": 734.7704121153201,
            "L": 874.4401638293348,
            "mean_service_time": 10.0
        },
        {
            "id": 45,
            "x": 41.60333623572382,
            "y": 85.37786465250578,
            "demand": 20,
            "E": 778.6083903820177,
            "L": 850.2330027418059,
            "mean_service_time": 10.0
        },
        {
            "id": 46,
            "x": 70.52690690947907,
            "y": 56.40361876669977,
            "demand": 23,
            "E": 734.9448869419926,
            "L": 840.9662045296886,
            "mean_service_time": 10.0
        },
        {
            "id": 47,
            "x": 56.3987350388659,
            "y": 12.115717642080536,
            "demand": 24,
            "E": 612.5077989565244,
            "L": 727.4216711643818,
            "mean_service_time": 10.0
        },
        {
            "id": 48,
            "x": 32.29072822153729,
            "y": 45.83423669842157,
            "demand": 23,
            "E": 716.0614052537268,
            "L": 879.5903135772676,
            "mean_service_time": 10.0
        },
        {
            "id": 49,
            "x": 51.6818828152453,
            "y": 82.76627818984724,
            "demand": 22,
            "E": 823.050753682829,
            "L": 932.7509221668621,
            "mean_service_time": 10.0
        },
        {
            "id": 50,
            "x": 26.970247256510582,
            "y": 58.2614076317435,
            "demand": 18,
            "E": 721.9371907117891,
            "L": 829.573467743598,
            "mean_service_time": 10.0
        }
    ]
}